mlchain/__init__.py
mlchain/__main__.py
mlchain/config.py
mlchain/context.py
mlchain/base/__init__.py
mlchain/base/converter.py
mlchain/base/exceptions.py
mlchain/base/gunicorn_config.py
mlchain/base/log.py
mlchain/base/serializer.py
mlchain/base/serve_model.py
mlchain/base/utils.py
mlchain/base/wrapper.py
mlchain/cli/__init__.py
mlchain/cli/artifact.py
mlchain/cli/init.py
mlchain/cli/main.py
mlchain/cli/mlchain_server.py
mlchain/cli/mlconfig.yaml
mlchain/cli/run.py
mlchain/cli/serve.py
mlchain/client/__init__.py
mlchain/client/base.py
mlchain/client/http_client.py
mlchain/decorators/__init__.py
mlchain/decorators/except_serving.py
mlchain/server/__init__.py
mlchain/server/authentication.py
mlchain/server/autofrontend.py
mlchain/server/base.py
mlchain/server/flask_server.py
mlchain/server/format.py
mlchain/server/starlette_server.py
mlchain/server/swagger.py
mlchain/server/view.py
mlchain/server/static/6xK3dSBYKcSV-LCoeQqfX1RYOo3qN67lujVj9_mf.woff2
mlchain/server/static/6xK3dSBYKcSV-LCoeQqfX1RYOo3qNa7lujVj9_mf.woff2
mlchain/server/static/6xK3dSBYKcSV-LCoeQqfX1RYOo3qNq7lujVj9_mf.woff2
mlchain/server/static/6xK3dSBYKcSV-LCoeQqfX1RYOo3qOK7lujVj9w.woff2
mlchain/server/static/6xK3dSBYKcSV-LCoeQqfX1RYOo3qPK7lujVj9_mf.woff2
mlchain/server/static/6xKydSBYKcSV-LCoeQqfX1RYOo3ig4vwkxdu3cOWxy40.woff2
mlchain/server/static/6xKydSBYKcSV-LCoeQqfX1RYOo3ig4vwlBdu3cOWxy40.woff2
mlchain/server/static/6xKydSBYKcSV-LCoeQqfX1RYOo3ig4vwlxdu3cOWxw.woff2
mlchain/server/static/6xKydSBYKcSV-LCoeQqfX1RYOo3ig4vwmBdu3cOWxy40.woff2
mlchain/server/static/6xKydSBYKcSV-LCoeQqfX1RYOo3ig4vwmRdu3cOWxy40.woff2
mlchain/server/static/6xKydSBYKcSV-LCoeQqfX1RYOo3ig4vwmhdu3cOWxy40.woff2
mlchain/server/static/6xKydSBYKcSV-LCoeQqfX1RYOo3ig4vwmxdu3cOWxy40.woff2
mlchain/server/static/Source-Sans-Pro.css
mlchain/server/static/image_1.svg
mlchain/server/static/image_2.svg
mlchain/server/static/mlchain.ico
mlchain/server/static/mlchain_fig_1.png
mlchain/server/static/mlchain_logo.png
mlchain-0.3.1.dist-info/LICENSE
mlchain-0.3.1.dist-info/METADATA
mlchain-0.3.1.dist-info/WHEEL
mlchain-0.3.1.dist-info/entry_points.txt
mlchain-0.3.1.dist-info/top_level.txt
mlchain-0.3.1.dist-info/RECORD
