Metadata-Version: 2.1
Name: mlchain
Version: 0.3.1
Summary: MLchain Python Library
Home-page: http://github.com/Techainer/mlchain-python
Author: Techainer Inc.
Author-email: admin@techainer.com
License: UNKNOWN
Keywords: mlchain,development,deployment ai,ai,artificial neural network,training,deploy,deployment,monitoring,model,deep learning,machine learning
Platform: UNKNOWN
Classifier: Intended Audience :: Developers
Classifier: Topic :: Software Development :: Libraries
Classifier: License :: OSI Approved :: MIT License
Classifier: Programming Language :: Python :: 3.6
Classifier: Programming Language :: Python :: 3.7
Classifier: Programming Language :: Python :: 3.8
Classifier: Programming Language :: Python :: 3.9
Requires-Python: >=3
Requires-Dist: attrs (>=20.3.0)
Requires-Dist: h11 (==0.14.0)
Requires-Dist: Flask (==2.2.2)
Requires-Dist: Flask-Cors (==3.0.10)
Requires-Dist: gunicorn (==20.1.0)
Requires-Dist: gevent (==22.10.2)
Requires-Dist: msgpack (==1.0.4)
Requires-Dist: opencv-python (>=4.5.1)
Requires-Dist: Pillow (>=8.0.1)
Requires-Dist: starlette[full] (==0.22.0)
Requires-Dist: requests (>=2.25.1)
Requires-Dist: six (>=1.13.0)
Requires-Dist: toml (>=0.10.0)
Requires-Dist: urllib3 (>=1.26.2)
Requires-Dist: uvicorn[standard] (==0.20.0)
Requires-Dist: httpx (==0.23.1)
Requires-Dist: boto3 (>=1.16.43)
Requires-Dist: pyyaml (>=5.3.1)
Requires-Dist: sentry-sdk[flask] (>=1.5.12)
Requires-Dist: thefuzz (==0.19.0)
Requires-Dist: python-Levenshtein (==0.20.8)
Requires-Dist: GPUtil (==1.4.0)
Requires-Dist: tqdm
Requires-Dist: pyngrok (>=5.1.0)
Requires-Dist: pynvml (==11.4.1)
Requires-Dist: numpy (<=1.21.6) ; python_version <= "3.7"
Requires-Dist: numpy (<1.20) ; python_version == "3.6"
Requires-Dist: numpy (<=1.22.4) ; python_version > "3.7"
Requires-Dist: blosc (==1.10.6) ; sys_platform != "win32"
Requires-Dist: uvloop (==0.14.0) ; sys_platform != "win32" and python_version == "3.6"
Requires-Dist: uvloop (==0.16.0) ; sys_platform != "win32" and python_version >= "3.7"
